CHANGES.txt
DEPENDENCES.txt
README.txt
setup.py
src/ng/__init__.py
src/ng.ftp.egg-info/PKG-INFO
src/ng.ftp.egg-info/SOURCES.txt
src/ng.ftp.egg-info/dependency_links.txt
src/ng.ftp.egg-info/namespace_packages.txt
src/ng.ftp.egg-info/not-zip-safe
src/ng.ftp.egg-info/requires.txt
src/ng.ftp.egg-info/top_level.txt
src/ng/ftp/TODO.txt
src/ng/ftp/__init__.py
src/ng/ftp/attributefactory.py
src/ng/ftp/configure.zcml
src/ng/ftp/interfaces.py
src/ng/ftp/ng.ftp.txt
src/ng/ftp/nsat.py
src/ng/ftp/readannotations.py
src/ng/ftp/readattribute.py
src/ng/ftp/readattributes.py
src/ng/ftp/readdirectory.py
src/ng/ftp/readnotdirectory.py
src/ng/ftp/utils.py
src/ng/ftp/writeattribute.py
src/ng/ftp/writeattributes.py
src/ng/ftp/writedirectory.py
src/ng/ftp/default/__init__.py
src/ng/ftp/default/attributediradapter.py
src/ng/ftp/default/configure.zcml
src/ng/ftp/default/directoryfactory.py
src/ng/ftp/etc/ng.ftp-configure.zcml
src/ng/ftp/etc/ng.ftp.default-configure.zcml
src/ng/ftp/widget/__init__.py
src/ng/ftp/widget/configure.zcml
src/ng/ftp/widget/ftpinterfacewidget.py
src/ng/ftp/widget/ftpobjectwidget.py
src/ng/ftp/widget/ftpwidget.py
src/ng/ftp/widget/interfaces.py
src/ng/ftp/widget/nsannotations4object.py
src/ng/ftp/widget/nsat4object.py
